README.rst
setup.py
steno3d_surfer/__init__.py
steno3d_surfer/parser.py
steno3d_surfer.egg-info/PKG-INFO
steno3d_surfer.egg-info/SOURCES.txt
steno3d_surfer.egg-info/dependency_links.txt
steno3d_surfer.egg-info/requires.txt
steno3d_surfer.egg-info/top_level.txt