Metadata-Version: 1.1
Name: steno3d-surfer
Version: 0.0.4
Summary: steno3d_surfer
Home-page: https://steno3d.com/
Author: Seequent
Author-email: support@steno3d.com
License: MIT License
Download-URL: http://github.com/seequent/steno3d-surfer
Keywords: visualization
Platform: Windows
Platform: Linux
Platform: Solaris
Platform: Mac OS-X
Platform: Unix
Classifier: Development Status :: 4 - Beta
Classifier: Programming Language :: Python
Classifier: Topic :: Scientific/Engineering
Classifier: Topic :: Scientific/Engineering :: Mathematics
Classifier: Topic :: Scientific/Engineering :: Physics
Classifier: Operating System :: Microsoft :: Windows
Classifier: Operating System :: POSIX
Classifier: Operating System :: Unix
Classifier: Operating System :: MacOS
Classifier: Natural Language :: English
